COPYING
ChangeLog
MANIFEST.in
NEWS
README
setup.cfg
setup.py
tox.ini
docs/changes.rst
docs/conf.py
docs/index.rst
docs/stdnum.ad.nrt.rst
docs/stdnum.al.nipt.rst
docs/stdnum.ar.cbu.rst
docs/stdnum.ar.cuit.rst
docs/stdnum.ar.dni.rst
docs/stdnum.at.businessid.rst
docs/stdnum.at.postleitzahl.rst
docs/stdnum.at.tin.rst
docs/stdnum.at.uid.rst
docs/stdnum.at.vnr.rst
docs/stdnum.au.abn.rst
docs/stdnum.au.acn.rst
docs/stdnum.au.tfn.rst
docs/stdnum.be.iban.rst
docs/stdnum.be.vat.rst
docs/stdnum.bg.egn.rst
docs/stdnum.bg.pnf.rst
docs/stdnum.bg.vat.rst
docs/stdnum.bic.rst
docs/stdnum.bitcoin.rst
docs/stdnum.br.cnpj.rst
docs/stdnum.br.cpf.rst
docs/stdnum.by.unp.rst
docs/stdnum.ca.bn.rst
docs/stdnum.ca.sin.rst
docs/stdnum.casrn.rst
docs/stdnum.ch.esr.rst
docs/stdnum.ch.ssn.rst
docs/stdnum.ch.uid.rst
docs/stdnum.ch.vat.rst
docs/stdnum.cl.rut.rst
docs/stdnum.cn.ric.rst
docs/stdnum.cn.uscc.rst
docs/stdnum.co.nit.rst
docs/stdnum.cr.cpf.rst
docs/stdnum.cr.cpj.rst
docs/stdnum.cr.cr.rst
docs/stdnum.cu.ni.rst
docs/stdnum.cusip.rst
docs/stdnum.cy.vat.rst
docs/stdnum.cz.dic.rst
docs/stdnum.cz.rc.rst
docs/stdnum.damm.rst
docs/stdnum.de.handelsregisternummer.rst
docs/stdnum.de.idnr.rst
docs/stdnum.de.stnr.rst
docs/stdnum.de.vat.rst
docs/stdnum.de.wkn.rst
docs/stdnum.dk.cpr.rst
docs/stdnum.dk.cvr.rst
docs/stdnum.do.cedula.rst
docs/stdnum.do.ncf.rst
docs/stdnum.do.rnc.rst
docs/stdnum.ean.rst
docs/stdnum.ec.ci.rst
docs/stdnum.ec.ruc.rst
docs/stdnum.ee.ik.rst
docs/stdnum.ee.kmkr.rst
docs/stdnum.ee.registrikood.rst
docs/stdnum.es.ccc.rst
docs/stdnum.es.cif.rst
docs/stdnum.es.cups.rst
docs/stdnum.es.dni.rst
docs/stdnum.es.iban.rst
docs/stdnum.es.nie.rst
docs/stdnum.es.nif.rst
docs/stdnum.es.referenciacatastral.rst
docs/stdnum.eu.at_02.rst
docs/stdnum.eu.banknote.rst
docs/stdnum.eu.eic.rst
docs/stdnum.eu.nace.rst
docs/stdnum.eu.vat.rst
docs/stdnum.exceptions.rst
docs/stdnum.fi.alv.rst
docs/stdnum.fi.associationid.rst
docs/stdnum.fi.hetu.rst
docs/stdnum.fi.veronumero.rst
docs/stdnum.fi.ytunnus.rst
python_stdnum_do.egg-info/PKG-INFO
python_stdnum_do.egg-info/SOURCES.txt
python_stdnum_do.egg-info/dependency_links.txt
python_stdnum_do.egg-info/requires.txt
python_stdnum_do.egg-info/top_level.txt
